LICENSE
README.md
setup.cfg
setup.py
pypatcher/__init__.py
pypatcher/__main__.py
pypatcher/errors.py
pypatcher/patcher.py
pypatcher.egg-info/PKG-INFO
pypatcher.egg-info/SOURCES.txt
pypatcher.egg-info/dependency_links.txt
pypatcher.egg-info/requires.txt
pypatcher.egg-info/top_level.txt