Metadata-Version: 2.1
Name: pypatcher
Version: 0.11
Summary: Utility module for handling incremental git patches
Home-page: https://github.com/sgtpepper9907/pypatcher
Author: David Angulo
Author-email: david.angulo.arias@gmail.com
License: GPL-3.0
Keywords: git,patches,incremental
License-File: LICENSE
